NetkillerJava/README.md
NetkillerJava/__init__.py
NetkillerJava/__main__.py
NetkillerJava/file.epub
NetkillerJava/index.html
NetkillerJava/css/__init__.py
NetkillerJava/css/annotations.css
NetkillerJava/css/main.css
NetkillerJava/css/normalize.css
NetkillerJava/css/popup.css
NetkillerJava/font/__init__.py
NetkillerJava/font/fontello.eot
NetkillerJava/font/fontello.svg
NetkillerJava/font/fontello.ttf
NetkillerJava/font/fontello.woff
NetkillerJava/img/__init__.py
NetkillerJava/img/annotator-glyph-sprite.png
NetkillerJava/img/annotator-icon-sprite.png
NetkillerJava/img/apple-touch-icon.png
NetkillerJava/img/cancelfullscreen.png
NetkillerJava/img/close.png
NetkillerJava/img/fullscreen.png
NetkillerJava/img/loader.gif
NetkillerJava/img/menu-icon.png
NetkillerJava/img/save.png
NetkillerJava/img/saved.png
NetkillerJava/img/settings-s.png
NetkillerJava/img/settings.png
NetkillerJava/img/star.png
NetkillerJava/js/__init__.py
NetkillerJava/js/epub.js
NetkillerJava/js/epub.min.js
NetkillerJava/js/epub.min.map
NetkillerJava/js/hooks.min.js
NetkillerJava/js/hooks.min.map
NetkillerJava/js/reader.js
NetkillerJava/js/reader.js.map
NetkillerJava/js/reader.min.js
NetkillerJava/js/reader.min.map
NetkillerJava/js/hooks/__init__.py
NetkillerJava/js/hooks/extensions/__init__.py
NetkillerJava/js/hooks/extensions/highlight.js
NetkillerJava/js/libs/__init__.py
NetkillerJava/js/libs/jquery.min.js
NetkillerJava/js/libs/localforage.min.js
NetkillerJava/js/libs/screenfull.js
NetkillerJava/js/libs/screenfull.min.js
NetkillerJava/js/libs/zip.min.js
NetkillerJava/js/plugins/__init__.py
NetkillerJava/js/plugins/hypothesis.js
NetkillerJava/js/plugins/search.js
netkiller_java-2024.3.5.0.dist-info/METADATA
netkiller_java-2024.3.5.0.dist-info/WHEEL
netkiller_java-2024.3.5.0.dist-info/entry_points.txt
netkiller_java-2024.3.5.0.dist-info/top_level.txt
netkiller_java-2024.3.5.0.dist-info/RECORD
